cep_to_coords/__init__.py
cep_to_coords/base.py
cep_to_coords/convert.py
cep_to_coords/strategies.py
cep_to_coords/viacep.py
tests/__init__.py
tests/test_convert.py
cep_to_coords-0.1.0.dist-info/LICENSE
cep_to_coords-0.1.0.dist-info/METADATA
cep_to_coords-0.1.0.dist-info/WHEEL
cep_to_coords-0.1.0.dist-info/top_level.txt
cep_to_coords-0.1.0.dist-info/RECORD
