Metadata-Version: 2.1
Name: cep-to-coords
Version: 0.1.0
Summary: Convert CEP (Brazilian zip code) to coordinates
Home-page: https://github.com/millengustavo/cep_to_coords
Author: Gustavo Millen
Author-email: millengustavo@gmail.com
License: UNKNOWN
Platform: UNKNOWN
Classifier: Programming Language :: Python :: 3
Classifier: License :: OSI Approved :: MIT License
Classifier: Operating System :: OS Independent
Requires-Python: >=3.6
